{
  "title": "syntcs",
  "subtitle": "CS2 Tools",
  "cards": [
    {
      "id": "lineups",
      "title": "Lineups",
      "description": "Smoke, Flash & Molotov lineups for every map",
      "url": "cs2/lineups",
      "badge": "",
      "badgeColor": "green",
      "enabled": true
    },
    {
      "id": "syntcs-config-1772959341492",
      "title": "Syntcs config",
      "description": "Syntcs's CS2 configs",
      "url": "cs2/cfg",
      "badge": "",
      "badgeColor": "green",
      "enabled": true
    }
  ]
}
